artheon_sast-2.0.dist-info/licenses/LICENSE
language_analyzer/__init__.py
language_analyzer/__main__.py
language_analyzer/csharp_vulnerabilities.py
language_analyzer/html_reporter.py
language_analyzer/java_vulnerabilities.py
language_analyzer/js_vulnerabilities.py
language_analyzer/python_vulnerabilities.py
language_analyzer/security_scanner.py
tests/__init__.py
tests/test_analyzer.py
artheon_sast-2.0.dist-info/METADATA
artheon_sast-2.0.dist-info/WHEEL
artheon_sast-2.0.dist-info/entry_points.txt
artheon_sast-2.0.dist-info/top_level.txt
artheon_sast-2.0.dist-info/RECORD
