Metadata-Version: 2.4
Name: artheon-sast
Version: 2.0
Summary: Static Application Security Testing tool for JavaScript, Python, Java, and C#
Home-page: https://github.com/DorianTitu/Artheon-SAST-Slim
Author: Dorian Tituaña, Ismael Toala
Author-email: dorian.tituana@epn.edu.ec, ismael.toala@epn.edu.ec
License: MIT
Project-URL: Homepage, https://github.com/DorianTitu/Artheon-SAST-Slim
Project-URL: Repository, https://github.com/DorianTitu/Artheon-SAST-Slim
Project-URL: Issues, https://github.com/DorianTitu/Artheon-SAST-Slim/issues
Keywords: sast,security,testing,javascript,python,java,csharp,vulnerability,scanner
Classifier: Development Status :: 4 - Beta
Classifier: Intended Audience :: Developers
Classifier: Intended Audience :: Information Technology
Classifier: License :: OSI Approved :: MIT License
Classifier: Programming Language :: Python :: 3
Classifier: Programming Language :: Python :: 3.8
Classifier: Programming Language :: Python :: 3.9
Classifier: Programming Language :: Python :: 3.10
Classifier: Programming Language :: Python :: 3.11
Classifier: Programming Language :: Python :: 3.12
Classifier: Topic :: Security
Classifier: Topic :: Software Development :: Quality Assurance
Requires-Python: >=3.8
License-File: LICENSE
Dynamic: author-email
Dynamic: home-page
Dynamic: license-file
Dynamic: requires-python
